covmatic_robotstation/__init__.py
covmatic_robotstation/robot.py
covmatic_robotstation/robot_api.py
covmatic_robotstation/robot_station.py
covmatic_robotstation-0.0.13.dist-info/METADATA
covmatic_robotstation-0.0.13.dist-info/WHEEL
covmatic_robotstation-0.0.13.dist-info/RECORD
