Metadata-Version: 2.1
Name: covmatic-robotstation
Version: 0.0.13
Summary: Extension of a Covmatic Station class that can control a RobotManager instance
Author-email: Agostino Facotti <agostino.facotti@asst-bergamoest.it>
Classifier: License :: OSI Approved :: MIT License
Classifier: Operating System :: OS Independent
Classifier: Programming Language :: Python :: 3
Requires-Python: >=3.7
Requires-Dist: covmatic-stations>=2.19.7
